sqlalchemy_fixture_factory/sqla_fix_fact.py
sqlalchemy_fixture_factory/__init__.py
SQLAlchemy_Fixture_Factory-1.0.0.dist-info/LICENSE.txt
SQLAlchemy_Fixture_Factory-1.0.0.dist-info/WHEEL
SQLAlchemy_Fixture_Factory-1.0.0.dist-info/metadata.json
SQLAlchemy_Fixture_Factory-1.0.0.dist-info/METADATA
SQLAlchemy_Fixture_Factory-1.0.0.dist-info/top_level.txt
SQLAlchemy_Fixture_Factory-1.0.0.dist-info/DESCRIPTION.rst
SQLAlchemy_Fixture_Factory-1.0.0.dist-info/RECORD
