Metadata-Version: 2.0
Name: SQLAlchemy-Fixture-Factory
Version: 1.0.0
Summary: Test Fixture Factory for SQLAlchemy. Inspired by Ruby's factory_girl
Home-page: https://github.com/mmmichl/sqlalchemy-fixture-factory
Author: Michael Pickelbauer
Author-email: mmmichlPi@gmail.com
License: MIT
Keywords: S,Q,L,A,l,c,h,e,m,y, ,t,e,s,t, ,f,i,x,t,u,r,e,s, ,d,a,t,a,b,a,s,e,-,t,e,s,t,i,n,g, ,s,c,e,n,a,r,i,o, ,b,u,i,l,d,e,r
Platform: a
Platform: n
Platform: y
Classifier: Development Status :: 5 - Production/Stable
Classifier: Intended Audience :: Developers
Classifier: Topic :: Software Development :: Testing
Classifier: Topic :: Database
Classifier: License :: OSI Approved :: MIT License
Classifier: Operating System :: OS Independent
Classifier: Programming Language :: Python
Classifier: Programming Language :: Python :: 2
Classifier: Programming Language :: Python :: 2.6
Classifier: Programming Language :: Python :: 2.7
Classifier: Programming Language :: Python :: 3
Classifier: Programming Language :: Python :: 3.2
Classifier: Programming Language :: Python :: 3.3
Classifier: Programming Language :: Python :: 3.4
Requires-Dist: SQLAlchemy (>=0.7)
